atooms/postprocessing/__init__.py
atooms/postprocessing/_version.py
atooms/postprocessing/alpha2.py
atooms/postprocessing/api.py
atooms/postprocessing/ba.py
atooms/postprocessing/chi4t.py
atooms/postprocessing/cl.py
atooms/postprocessing/cli.py
atooms/postprocessing/core.py
atooms/postprocessing/correlation.py
atooms/postprocessing/filter.py
atooms/postprocessing/fkt.py
atooms/postprocessing/fourierspace.f90
atooms/postprocessing/fourierspace.py
atooms/postprocessing/gr.py
atooms/postprocessing/helpers.py
atooms/postprocessing/ik.py
atooms/postprocessing/linkedcells.py
atooms/postprocessing/molecular.py
atooms/postprocessing/msd.py
atooms/postprocessing/oad.py
atooms/postprocessing/partial.py
atooms/postprocessing/progress.py
atooms/postprocessing/qt.py
atooms/postprocessing/realspace.f90
atooms/postprocessing/s4kt.py
atooms/postprocessing/sacf.py
atooms/postprocessing/sk.py
atooms/postprocessing/susceptibility.py
atooms/postprocessing/vacf.py
atooms/postprocessing/vanhove.py
atooms_pp-4.2.1.data/scripts/pp.py
atooms_pp-4.2.1.dist-info/licenses/LICENSE
atooms_pp-4.2.1.dist-info/METADATA
atooms_pp-4.2.1.dist-info/WHEEL
atooms_pp-4.2.1.dist-info/top_level.txt
atooms_pp-4.2.1.dist-info/RECORD
