Metadata-Version: 2.4
Name: atooms-pp
Version: 4.2.1
Summary: Post-processing tools for particle simulations
Author-email: Daniele Coslovich <daniele.coslovich@umontpellier.fr>
License: GPLv3
Project-URL: repository, https://framagit.org/atooms/postprocessing
Project-URL: homepage, https://framagit.org/atooms/postprocessing
Project-URL: documentation, https://atooms.frama.io/postprocessing
Project-URL: changelog, https://framagit.org/atooms/postprocessing/-/blob/master/CHANGELOG.md
Classifier: License :: OSI Approved :: GNU General Public License v3 (GPLv3)
Classifier: Development Status :: 5 - Production/Stable
Classifier: Programming Language :: Python :: 3
Classifier: Programming Language :: Python :: 3.7
Classifier: Programming Language :: Python :: 3.8
Classifier: Programming Language :: Python :: 3.9
Classifier: Programming Language :: Python :: 3.10
Classifier: Programming Language :: Python :: 3.11
Classifier: Programming Language :: Python :: 3.12
Classifier: Programming Language :: Python :: 3.13
Requires-Python: >=3.7
License-File: LICENSE
Requires-Dist: atooms>=3.27.0
Requires-Dist: argh
Requires-Dist: tqdm
Requires-Dist: f2py_jit
Dynamic: license-file
